kipi/__init__.py
kipi/checksum.py
kipi/kicad_getlibs.py
kipi/lib_table.py
kipi/semver.py
kipi/sexpdata.py
kipi/str_util.py
kipi/template.py
kipi/2018_03_31/__init__.py
kipi/2018_03_31/checksum.py
kipi/2018_03_31/kicad_getlibs.py
kipi/2018_03_31/lib_table.py
kipi/2018_03_31/semver.py
kipi/2018_03_31/str_util.py
kipi/2018_03_31/template.py
kipi-0.2.1.dist-info/DESCRIPTION.rst
kipi-0.2.1.dist-info/METADATA
kipi-0.2.1.dist-info/RECORD
kipi-0.2.1.dist-info/WHEEL
kipi-0.2.1.dist-info/entry_points.txt
kipi-0.2.1.dist-info/metadata.json
kipi-0.2.1.dist-info/top_level.txt
