Metadata-Version: 2.0
Name: kipi
Version: 0.2.1
Summary: A tool for downloading and installing KiCad packages
Home-page: https://github.com/bobc/kicad-getlibs
Author: Bob Cousins
Author-email: bobcousins42@googlemail.com
License: UNKNOWN
Project-URL: Source, https://github.com/bobc/kicad-getlibs/
Project-URL: Bug Reports, https://github.com/bobc/kicad-getlibs/issues
Keywords: kicad package installer
Platform: UNKNOWN
Classifier: Development Status :: 3 - Alpha
Classifier: Intended Audience :: Manufacturing
Classifier: Topic :: Scientific/Engineering :: Electronic Design Automation (EDA)
Classifier: License :: OSI Approved :: MIT License
Classifier: Programming Language :: Python :: 2
Classifier: Programming Language :: Python :: 2.7
Requires-Dist: psutil
Requires-Dist: pyyaml
